dockerutils/__init__.py
dockerutils/_version.py
dockerutils/cd.py
dockerutils/docker-server-daemon.json
dockerutils/gen_version.py
dockerutils/image_conventions.py
dockerutils/pip_conf.py
dockerutils-2.0.7.data/scripts/build-image
dockerutils-2.0.7.data/scripts/create-dock
dockerutils-2.0.7.data/scripts/destroy-dock
dockerutils-2.0.7.data/scripts/dock
dockerutils-2.0.7.data/scripts/dock-sync
dockerutils-2.0.7.data/scripts/genversion
dockerutils-2.0.7.data/scripts/ls-dock
dockerutils-2.0.7.data/scripts/nb-dock
dockerutils-2.0.7.data/scripts/publish-image
dockerutils-2.0.7.data/scripts/register-dock
dockerutils-2.0.7.data/scripts/run-image
dockerutils-2.0.7.data/scripts/run-notebook
dockerutils-2.0.7.data/scripts/ssh-dock
dockerutils-2.0.7.data/scripts/start-dock
dockerutils-2.0.7.data/scripts/stop-dock
dockerutils-2.0.7.data/scripts/transfer-image
dockerutils-2.0.7.data/scripts/unregister-dock
dockerutils-2.0.7.dist-info/LICENSE
dockerutils-2.0.7.dist-info/METADATA
dockerutils-2.0.7.dist-info/WHEEL
dockerutils-2.0.7.dist-info/top_level.txt
dockerutils-2.0.7.dist-info/RECORD
