Metadata-Version: 2.1
Name: dockerutils
Version: 2.0.7
Summary: Docker Utilities/Patterns for Python Projects
Home-page: https://github.com/resero-labs/docker-utils.git
Author: Resero-Labs
License: MIT License
Platform: UNKNOWN
Classifier: Development Status :: 5 - Production/Stable
Classifier: Intended Audience :: Developers
Classifier: Natural Language :: English
Classifier: License :: OSI Approved :: MIT License
Classifier: Programming Language :: Python :: 2.7
Classifier: Programming Language :: Python :: 3.4
Classifier: Programming Language :: Python :: 3.5
Classifier: Programming Language :: Python :: 3.6
Classifier: Programming Language :: Python :: 3.7
Requires-Dist: awscli
Requires-Dist: boto3
Requires-Dist: future
Requires-Dist: ConfigParser ; python_version <= "2.7"
Provides-Extra: dev
Requires-Dist: wheel (>=0.29) ; extra == 'dev'
Provides-Extra: test
Requires-Dist: pytest (>=3.0) ; extra == 'test'
Requires-Dist: pytest-cov (>=2.4) ; extra == 'test'
Requires-Dist: pylint (>=1.8.1) ; extra == 'test'
